{
    "": {
        "TimeRelease": {
            "year": 2025,
            "day": 30,
            "month": 4
        },
        "TimeExpired": {
            "year": 2025,
            "day": 31,
            "month": 5
        },
        "Rewards": {
            "NumberValue": {
                "Gems": 1000,
                "Gold": 3500
            }
        }
    },
    "": {
        "TimeRelease": {
            "year": 2025,
            "day": 10,
            "month": 5
        },
        "TimeExpired": {
            "year": 2025,
            "day": 18,
            "month": 5
        },
        "Rewards": {
            "NumberValue": {
                "Gems": 1000
            },
            "Items": {
                "TraitReroll": 10,
                "Spell": 10
            }
        }
    }
}
